textractmanifest/__init__.py
textractmanifest/manifest.py
schadem_tidp_manifest-0.0.11.dist-info/LICENSE
schadem_tidp_manifest-0.0.11.dist-info/METADATA
schadem_tidp_manifest-0.0.11.dist-info/WHEEL
schadem_tidp_manifest-0.0.11.dist-info/top_level.txt
schadem_tidp_manifest-0.0.11.dist-info/RECORD
