Metadata-Version: 2.1
Name: schadem-tidp-manifest
Version: 0.0.11
Summary: Amazon Textract IDP Manifest
Home-page: https://github.com/schadem/schadem-tidp-manifest/tree/mainline
Author: Amazon Rekognition Textract Demoes
Author-email: rekognition-textract-demos@amazon.com
License: Apache License Version 2.0
Keywords: textract manifest
Classifier: Development Status :: 4 - Beta
Classifier: Topic :: Utilities
Classifier: License :: OSI Approved :: Apache Software License
Classifier: Programming Language :: Python :: 3.7
Classifier: Programming Language :: Python :: 3.8
Classifier: Programming Language :: Python :: 3.9
Requires-Python: >=3.7
License-File: LICENSE
Requires-Dist: marshmallow
Provides-Extra: testing
Requires-Dist: pytest ; extra == 'testing'
